ultralytics/__init__.py
ultralytics/assets/bus.jpg
ultralytics/assets/zidane.jpg
ultralytics/cfg/__init__.py
ultralytics/cfg/default.yaml
ultralytics/cfg/datasets/Argoverse.yaml
ultralytics/cfg/datasets/DOTAv2.yaml
ultralytics/cfg/datasets/GlobalWheat2020.yaml
ultralytics/cfg/datasets/ImageNet.yaml
ultralytics/cfg/datasets/Objects365.yaml
ultralytics/cfg/datasets/SKU-110K.yaml
ultralytics/cfg/datasets/VOC.yaml
ultralytics/cfg/datasets/VisDrone.yaml
ultralytics/cfg/datasets/coco-pose.yaml
ultralytics/cfg/datasets/coco.yaml
ultralytics/cfg/datasets/coco128-seg.yaml
ultralytics/cfg/datasets/coco128.yaml
ultralytics/cfg/datasets/coco8-pose.yaml
ultralytics/cfg/datasets/coco8-seg.yaml
ultralytics/cfg/datasets/coco8.yaml
ultralytics/cfg/datasets/open-images-v7.yaml
ultralytics/cfg/datasets/xView.yaml
ultralytics/cfg/models/rt-detr/rtdetr-l.yaml
ultralytics/cfg/models/rt-detr/rtdetr-x.yaml
ultralytics/cfg/models/v3/yolov3-spp.yaml
ultralytics/cfg/models/v3/yolov3-tiny.yaml
ultralytics/cfg/models/v3/yolov3.yaml
ultralytics/cfg/models/v5/yolov5-p6.yaml
ultralytics/cfg/models/v5/yolov5.yaml
ultralytics/cfg/models/v6/yolov6.yaml
ultralytics/cfg/models/v8/yolov8-cls.yaml
ultralytics/cfg/models/v8/yolov8-p2.yaml
ultralytics/cfg/models/v8/yolov8-p6.yaml
ultralytics/cfg/models/v8/yolov8-pose-p6.yaml
ultralytics/cfg/models/v8/yolov8-pose.yaml
ultralytics/cfg/models/v8/yolov8-rtdetr.yaml
ultralytics/cfg/models/v8/yolov8-seg.yaml
ultralytics/cfg/models/v8/yolov8.yaml
ultralytics/cfg/trackers/botsort.yaml
ultralytics/cfg/trackers/bytetrack.yaml
ultralytics/data/__init__.py
ultralytics/data/annotator.py
ultralytics/data/augment.py
ultralytics/data/base.py
ultralytics/data/build.py
ultralytics/data/converter.py
ultralytics/data/dataset.py
ultralytics/data/loaders.py
ultralytics/data/utils.py
ultralytics/engine/__init__.py
ultralytics/engine/exporter.py
ultralytics/engine/model.py
ultralytics/engine/predictor.py
ultralytics/engine/results.py
ultralytics/engine/trainer.py
ultralytics_rknn-12.0.1.dist-info/LICENSE
ultralytics_rknn-12.0.1.dist-info/METADATA
ultralytics_rknn-12.0.1.dist-info/WHEEL
ultralytics_rknn-12.0.1.dist-info/entry_points.txt
ultralytics_rknn-12.0.1.dist-info/top_level.txt
ultralytics_rknn-12.0.1.dist-info/RECORD
